{
  "updated_at": "2026-04-26T09:47:16+00:00",
  "currencies": {
    "USD": {
      "buy": 155100.0,
      "sell": 156650.0,
      "timestamp": "2026-04-26T09:47:16+00:00"
    },
    "EUR": {
      "buy": 181800.0,
      "sell": 183600.0,
      "timestamp": "2026-04-26T09:47:16+00:00"
    },
    "AED": {
      "buy": 42190.0,
      "sell": 42620.0,
      "timestamp": "2026-04-26T09:47:16+00:00"
    },
    "TRY": {
      "buy": 3410.0,
      "sell": 3550.0,
      "timestamp": "2026-04-26T09:47:16+00:00"
    },
    "GBP": {
      "buy": 208700.0,
      "sell": 211900.0,
      "timestamp": "2026-04-26T09:47:16+00:00"
    },
    "CNY": {
      "buy": 22460.0,
      "sell": 22920.0,
      "timestamp": "2026-04-26T09:47:16+00:00"
    },
    "CAD": {
      "buy": 112900.0,
      "sell": 114600.0,
      "timestamp": "2026-04-26T09:47:16+00:00"
    },
    "AUD": {
      "buy": 110300.0,
      "sell": 112000.0,
      "timestamp": "2026-04-26T09:47:16+00:00"
    },
    "RUB": {
      "buy": 2040.0,
      "sell": 2080.0,
      "timestamp": "2026-04-26T09:47:16+00:00"
    },
    "IQD": {
      "buy": 108.7,
      "sell": 110.9,
      "timestamp": "2026-04-26T09:47:16+00:00"
    },
    "MYR": {
      "buy": 38320.0,
      "sell": 39500.0,
      "timestamp": "2026-04-26T09:47:16+00:00"
    },
    "GEL": {
      "buy": 57100.0,
      "sell": 58300.0,
      "timestamp": "2026-04-26T09:47:16+00:00"
    },
    "AZN": {
      "buy": 90300.0,
      "sell": 92100.0,
      "timestamp": "2026-04-26T09:47:16+00:00"
    },
    "AMD": {
      "buy": 412.8,
      "sell": 421.2,
      "timestamp": "2026-04-26T09:47:16+00:00"
    },
    "THB": {
      "buy": 4740.0,
      "sell": 4840.0,
      "timestamp": "2026-04-26T09:47:16+00:00"
    },
    "OMR": {
      "buy": 399000.0,
      "sell": 407100.0,
      "timestamp": "2026-04-26T09:47:16+00:00"
    },
    "INR": {
      "buy": 1630.0,
      "sell": 1660.0,
      "timestamp": "2026-04-26T09:47:16+00:00"
    },
    "PKR": {
      "buy": 551.0,
      "sell": 562.0,
      "timestamp": "2026-04-26T09:47:16+00:00"
    },
    "JPY": {
      "buy": 963.0,
      "sell": 983.0,
      "timestamp": "2026-04-26T09:47:16+00:00"
    },
    "SAR": {
      "buy": 40920.0,
      "sell": 41760.0,
      "timestamp": "2026-04-26T09:47:16+00:00"
    },
    "AFN": {
      "buy": 2390.0,
      "sell": 2440.0,
      "timestamp": "2026-04-26T09:47:16+00:00"
    },
    "SEK": {
      "buy": 16660.0,
      "sell": 17000.0,
      "timestamp": "2026-04-26T09:47:16+00:00"
    },
    "CHF": {
      "buy": 195500.0,
      "sell": 199500.0,
      "timestamp": "2026-04-26T09:47:16+00:00"
    },
    "QAR": {
      "buy": 42100.0,
      "sell": 42960.0,
      "timestamp": "2026-04-26T09:47:16+00:00"
    },
    "KRW": {
      "buy": 104.0,
      "sell": 106.1,
      "timestamp": "2026-04-26T09:47:16+00:00"
    },
    "NOK": {
      "buy": 16320.0,
      "sell": 16820.0,
      "timestamp": "2026-04-26T09:47:16+00:00"
    },
    "NZD": {
      "buy": 89340.0,
      "sell": 92100.0,
      "timestamp": "2026-04-26T09:47:16+00:00"
    },
    "SGD": {
      "buy": 119020.0,
      "sell": 122700.0,
      "timestamp": "2026-04-26T09:47:16+00:00"
    },
    "HKD": {
      "buy": 19400.0,
      "sell": 20000.0,
      "timestamp": "2026-04-26T09:47:16+00:00"
    },
    "KWD": {
      "buy": 493660.0,
      "sell": 508920.0,
      "timestamp": "2026-04-26T09:47:16+00:00"
    },
    "DKK": {
      "buy": 23840.0,
      "sell": 24580.0,
      "timestamp": "2026-04-26T09:47:16+00:00"
    },
    "BHD": {
      "buy": 402500.0,
      "sell": 414940.0,
      "timestamp": "2026-04-26T09:47:16+00:00"
    },
    "TJS": {
      "buy": 16100.0,
      "sell": 16600.0,
      "timestamp": "2026-04-26T09:47:16+00:00"
    },
    "TMT": {
      "buy": 43420.0,
      "sell": 44760.0,
      "timestamp": "2026-04-26T09:47:16+00:00"
    },
    "KGS": {
      "buy": 1735.0,
      "sell": 1790.0,
      "timestamp": "2026-04-26T09:47:16+00:00"
    },
    "SYP": {
      "buy": 1315.55,
      "sell": 1356.25,
      "timestamp": "2026-04-26T09:47:16+00:00"
    },
    "BRL": {
      "buy": 30520.0,
      "sell": 31460.0,
      "timestamp": "2026-04-26T09:47:16+00:00"
    },
    "ARS": {
      "buy": 109.0,
      "sell": 112.0,
      "timestamp": "2026-04-26T09:47:16+00:00"
    }
  }
}