{
  "updated_at": "2026-01-03T09:43:06+00:00",
  "currencies": {
    "USD": {
      "buy": 138150,
      "sell": 138250,
      "timestamp": "2026-01-03T09:43:06+00:00"
    },
    "EUR": {
      "buy": 161950,
      "sell": 162150,
      "timestamp": "2026-01-03T09:43:06+00:00"
    },
    "GBP": {
      "buy": 186000,
      "sell": 186200,
      "timestamp": "2026-01-03T09:43:06+00:00"
    },
    "CHF": {
      "buy": 174350,
      "sell": 174550,
      "timestamp": "2026-01-03T09:43:06+00:00"
    },
    "CAD": {
      "buy": 100550,
      "sell": 100650,
      "timestamp": "2026-01-03T09:43:06+00:00"
    },
    "AUD": {
      "buy": 92450,
      "sell": 92550,
      "timestamp": "2026-01-03T09:43:06+00:00"
    },
    "SEK": {
      "buy": 14900,
      "sell": 15000,
      "timestamp": "2026-01-03T09:43:06+00:00"
    },
    "NOK": {
      "buy": 13750,
      "sell": 13750,
      "timestamp": "2026-01-03T09:43:06+00:00"
    },
    "RUB": {
      "buy": 1715,
      "sell": 1720,
      "timestamp": "2026-01-03T09:43:06+00:00"
    },
    "THB": {
      "buy": 4385,
      "sell": 4390,
      "timestamp": "2026-01-03T09:43:06+00:00"
    },
    "SGD": {
      "buy": 107450,
      "sell": 107550,
      "timestamp": "2026-01-03T09:43:06+00:00"
    },
    "HKD": {
      "buy": 17650,
      "sell": 17750,
      "timestamp": "2026-01-03T09:43:06+00:00"
    },
    "AZN": {
      "buy": 81050,
      "sell": 81150,
      "timestamp": "2026-01-03T09:43:06+00:00"
    },
    "AMD": {
      "buy": 362.0,
      "sell": 362.5,
      "timestamp": "2026-01-03T09:43:06+00:00"
    },
    "DKK": {
      "buy": 21600,
      "sell": 21700,
      "timestamp": "2026-01-03T09:43:06+00:00"
    },
    "AED": {
      "buy": 37150,
      "sell": 37200,
      "timestamp": "2026-01-03T09:43:06+00:00"
    },
    "JPY": {
      "buy": 880.5,
      "sell": 881.5,
      "timestamp": "2026-01-03T09:43:06+00:00"
    },
    "TRY": {
      "buy": 3190,
      "sell": 3210,
      "timestamp": "2026-01-03T09:43:06+00:00"
    },
    "CNY": {
      "buy": 19750,
      "sell": 19750,
      "timestamp": "2026-01-03T09:43:06+00:00"
    },
    "SAR": {
      "buy": 36750,
      "sell": 36850,
      "timestamp": "2026-01-03T09:43:06+00:00"
    },
    "INR": {
      "buy": 1530,
      "sell": 1535,
      "timestamp": "2026-01-03T09:43:06+00:00"
    },
    "MYR": {
      "buy": 34000,
      "sell": 34100,
      "timestamp": "2026-01-03T09:43:06+00:00"
    },
    "AFN": {
      "buy": 2105,
      "sell": 2110,
      "timestamp": "2026-01-03T09:43:06+00:00"
    },
    "KWD": {
      "buy": 449450,
      "sell": 449850,
      "timestamp": "2026-01-03T09:43:06+00:00"
    },
    "IQD": {
      "buy": 105.5,
      "sell": 105.5,
      "timestamp": "2026-01-03T09:43:06+00:00"
    },
    "BHD": {
      "buy": 365350,
      "sell": 365850,
      "timestamp": "2026-01-03T09:43:06+00:00"
    },
    "OMR": {
      "buy": 358450,
      "sell": 358750,
      "timestamp": "2026-01-03T09:43:06+00:00"
    },
    "QAR": {
      "buy": 37850,
      "sell": 37950,
      "timestamp": "2026-01-03T09:43:06+00:00"
    }
  }
}